{
  "defaultLanguage": "en-GB",
  "defaultPrice": {
    "currency": "EUR",
    "priceMicros": "8000000"
  },
  "listings": {
    "en-GB": {
      "description": "Buy me a well seasoned pizza which will feed my brain",
      "title": "A pizza"
    }
  },
  "packageName": "com.gianlu.dnshero",
  "prices": {
    "DZ": {
      "currency": "DZD",
      "priceMicros": "1050000000"
    },
    "SA": {
      "currency": "SAR",
      "priceMicros": "35990000"
    },
    "AU": {
      "currency": "AUD",
      "priceMicros": "12990000"
    },
    "AT": {
      "currency": "EUR",
      "priceMicros": "9490000"
    },
    "BH": {
      "currency": "USD",
      "priceMicros": "9490000"
    },
    "BD": {
      "currency": "BDT",
      "priceMicros": "750000000"
    },
    "BE": {
      "currency": "EUR",
      "priceMicros": "9490000"
    },
    "BO": {
      "currency": "BOB",
      "priceMicros": "65990000"
    },
    "BR": {
      "currency": "BRL",
      "priceMicros": "29990000"
    },
    "BG": {
      "currency": "BGN",
      "priceMicros": "18990000"
    },
    "KH": {
      "currency": "USD",
      "priceMicros": "9490000"
    },
    "CA": {
      "currency": "CAD",
      "priceMicros": "11990000"
    },
    "CL": {
      "currency": "CLP",
      "priceMicros": "6000000000"
    },
    "CY": {
      "currency": "EUR",
      "priceMicros": "9490000"
    },
    "CO": {
      "currency": "COP",
      "priceMicros": "28000000000"
    },
    "KR": {
      "currency": "KRW",
      "priceMicros": "11000000000"
    },
    "CR": {
      "currency": "CRC",
      "priceMicros": "5500000000"
    },
    "HR": {
      "currency": "HRK",
      "priceMicros": "75000000"
    },
    "DK": {
      "currency": "DKK",
      "priceMicros": "75000000"
    },
    "EG": {
      "currency": "EGP",
      "priceMicros": "169990000"
    },
    "AE": {
      "currency": "AED",
      "priceMicros": "34990000"
    },
    "EE": {
      "currency": "EUR",
      "priceMicros": "9490000"
    },
    "RU": {
      "currency": "RUB",
      "priceMicros": "590000000"
    },
    "PH": {
      "currency": "PHP",
      "priceMicros": "489000000"
    },
    "FI": {
      "currency": "EUR",
      "priceMicros": "9990000"
    },
    "FR": {
      "currency": "EUR",
      "priceMicros": "9490000"
    },
    "DE": {
      "currency": "EUR",
      "priceMicros": "9490000"
    },
    "GH": {
      "currency": "GHS",
      "priceMicros": "40000000"
    },
    "JP": {
      "currency": "JPY",
      "priceMicros": "1050000000"
    },
    "GR": {
      "currency": "EUR",
      "priceMicros": "9990000"
    },
    "IN": {
      "currency": "INR",
      "priceMicros": "620000000"
    },
    "ID": {
      "currency": "IDR",
      "priceMicros": "129000000000"
    },
    "IE": {
      "currency": "EUR",
      "priceMicros": "9990000"
    },
    "IL": {
      "currency": "ILS",
      "priceMicros": "34000000"
    },
    "IT": {
      "currency": "EUR",
      "priceMicros": "9990000"
    },
    "KZ": {
      "currency": "KZT",
      "priceMicros": "3190000000"
    },
    "KE": {
      "currency": "KES",
      "priceMicros": "1000000000"
    },
    "KW": {
      "currency": "USD",
      "priceMicros": "9490000"
    },
    "LV": {
      "currency": "EUR",
      "priceMicros": "9490000"
    },
    "LB": {
      "currency": "LBP",
      "priceMicros": "14500000000"
    },
    "LI": {
      "currency": "CHF",
      "priceMicros": "9100000"
    },
    "LT": {
      "currency": "EUR",
      "priceMicros": "9490000"
    },
    "LU": {
      "currency": "EUR",
      "priceMicros": "9490000"
    },
    "MY": {
      "currency": "MYR",
      "priceMicros": "40990000"
    },
    "MA": {
      "currency": "MAD",
      "priceMicros": "88990000"
    },
    "MX": {
      "currency": "MXN",
      "priceMicros": "169000000"
    },
    "NG": {
      "currency": "NGN",
      "priceMicros": "3440000000"
    },
    "NO": {
      "currency": "NOK",
      "priceMicros": "95000000"
    },
    "NZ": {
      "currency": "NZD",
      "priceMicros": "14990000"
    },
    "OM": {
      "currency": "USD",
      "priceMicros": "9490000"
    },
    "NL": {
      "currency": "EUR",
      "priceMicros": "9490000"
    },
    "PK": {
      "currency": "PKR",
      "priceMicros": "1000000000"
    },
    "PE": {
      "currency": "PEN",
      "priceMicros": "30990000"
    },
    "PL": {
      "currency": "PLN",
      "priceMicros": "41990000"
    },
    "PT": {
      "currency": "EUR",
      "priceMicros": "9990000"
    },
    "QA": {
      "currency": "QAR",
      "priceMicros": "35000000"
    },
    "HK": {
      "currency": "HKD",
      "priceMicros": "75900000"
    },
    "GB": {
      "currency": "GBP",
      "priceMicros": "8990000"
    },
    "CZ": {
      "currency": "CZK",
      "priceMicros": "249990000"
    },
    "RO": {
      "currency": "RON",
      "priceMicros": "43990000"
    },
    "SG": {
      "currency": "SGD",
      "priceMicros": "12980000"
    },
    "SK": {
      "currency": "EUR",
      "priceMicros": "9490000"
    },
    "SI": {
      "currency": "EUR",
      "priceMicros": "9990000"
    },
    "ES": {
      "currency": "EUR",
      "priceMicros": "9490000"
    },
    "LK": {
      "currency": "LKR",
      "priceMicros": "1450000000"
    },
    "US": {
      "currency": "USD",
      "priceMicros": "9490000"
    },
    "ZA": {
      "currency": "ZAR",
      "priceMicros": "124990000"
    },
    "SE": {
      "currency": "SEK",
      "priceMicros": "95000000"
    },
    "CH": {
      "currency": "CHF",
      "priceMicros": "9100000"
    },
    "TH": {
      "currency": "THB",
      "priceMicros": "325000000"
    },
    "TW": {
      "currency": "TWD",
      "priceMicros": "300000000"
    },
    "TZ": {
      "currency": "TZS",
      "priceMicros": "21000000000"
    },
    "TR": {
      "currency": "TRY",
      "priceMicros": "32990000"
    },
    "UA": {
      "currency": "UAH",
      "priceMicros": "244990000"
    },
    "HU": {
      "currency": "HUF",
      "priceMicros": "3099000000"
    },
    "VN": {
      "currency": "VND",
      "priceMicros": "217000000000"
    },
    "MO": {
      "currency": "MOP",
      "priceMicros": "76880000"
    }
  },
  "purchaseType": "managedUser",
  "sku": "donation.pizza",
  "status": "active"
}